LICENSE
MANIFEST.in
README.md
runtests.sh
setup.py
django_googlytics.egg-info/PKG-INFO
django_googlytics.egg-info/SOURCES.txt
django_googlytics.egg-info/dependency_links.txt
django_googlytics.egg-info/not-zip-safe
django_googlytics.egg-info/top_level.txt
googlytics/__init__.py
googlytics/context_processors.py
googlytics/models.py
googlytics/tests.py
googlytics/templates/googlytics/googlytics.html