Metadata-Version: 1.1
Name: django-googlytics
Version: 0.2.1
Summary: Add google analytics snippet to your django templates.
Home-page: https://github.com/rikpg/django-googlytics
Author: Riccardo Poggi
Author-email: rik.poggi@gmail.com
License: BSD licence
Platform: UNKNOWN
Classifier: Development Status :: 4 - Beta
Classifier: Environment :: Web Environment
Classifier: Framework :: Django
Classifier: Intended Audience :: Developers
Classifier: License :: OSI Approved :: BSD License
Classifier: Natural Language :: English
Classifier: Programming Language :: Python
